pydexscreener/__init__.py
pydexscreener/dex.py
pydexscreener/Models/Pair.py
pydexscreener/Models/__init__.py
pydexscreener-0.0.1.1649305573.dist-info/METADATA
pydexscreener-0.0.1.1649305573.dist-info/WHEEL
pydexscreener-0.0.1.1649305573.dist-info/top_level.txt
pydexscreener-0.0.1.1649305573.dist-info/RECORD
